pychd/__init__.py
pychd/compile.py
pychd/decompile.py
pychd/main.py
pychd/types.py
pychd-0.2.4.dist-info/LICENSE
pychd-0.2.4.dist-info/METADATA
pychd-0.2.4.dist-info/WHEEL
pychd-0.2.4.dist-info/entry_points.txt
pychd-0.2.4.dist-info/top_level.txt
pychd-0.2.4.dist-info/RECORD
