Metadata-Version: 2.1
Name: pychd
Version: 0.2.4
Summary: The ChatGPT-powered decompiler for Python, providing superior code analysis capabilities
Author-email: 卍diohabara卍 <diohabara@users.noreply.github.com>
Requires-Python: >=3.12
License-File: LICENSE
Requires-Dist: openai >=1.35.3
Requires-Dist: xdis >=6.1.0
Requires-Dist: pre-commit >=3.7.1
